dlr/esy/grid/match/__init__.py
dlr/esy/grid/match/cli.py
dlr/esy/grid/match/cluster.py
dlr/esy/grid/match/geojson.py
dlr/esy/grid/match/powergrid.py
dlr/esy/grid/match/test.py
dlr/esy/grid/match/visualize.py
dlr_esy_grid_match-0.1.dist-info/LICENSE
dlr_esy_grid_match-0.1.dist-info/METADATA
dlr_esy_grid_match-0.1.dist-info/WHEEL
dlr_esy_grid_match-0.1.dist-info/entry_points.txt
dlr_esy_grid_match-0.1.dist-info/top_level.txt
dlr_esy_grid_match-0.1.dist-info/RECORD
