Metadata-Version: 2.1
Name: dlr-esy-grid-match
Version: 0.1
Summary: grid matching & conversion tool
Author-email: Oriol Raventós Morera <oriol.raventosmorera@dlr.de>, Ontje Lünsdorf <ontje.luensdorf@dlr.de>, Theresa Klütz <t.kluetz@fz-juelich.de>, Abhilash Bandam <a.bandam@fz-juelich.de>
Project-URL: homepage, https://gitlab.com/dlr-ve/esy/dlr.esy.grid.match
Project-URL: documentation, https://dlr-ve.gitlab.io/esy/dlr.esy.grid.match
Project-URL: tracker, https://gitlab.com/dlr-ve/esy/dlr.esy.grid.match/issues
Keywords: OSM,OpenStreetMap,power grid,graph,energy modelling
Classifier: Development Status :: 5 - Production/Stable
Classifier: Environment :: Console
Classifier: Intended Audience :: Developers
Classifier: Intended Audience :: Education
Classifier: Intended Audience :: Science/Research
Classifier: License :: OSI Approved :: MIT License
Classifier: Natural Language :: English
Classifier: Operating System :: OS Independent
Classifier: Programming Language :: Python
Classifier: Programming Language :: Python :: 3
Classifier: Topic :: Scientific/Engineering
Requires-Python: >=3.9
License-File: LICENSE
Requires-Dist: numpy >=1.23
Requires-Dist: scipy >=1.12
Requires-Dist: matplotlib >=3.8
Provides-Extra: dev
Requires-Dist: pdoc ; extra == 'dev'
